sassy/__init__.py
sassy/__pycache__/__init__.pypy39.pyc
sassy/example.py
sassy/sassy.cpython-311-x86_64-linux-gnu.so
simd_sassy-0.1.0.dist-info/METADATA
simd_sassy-0.1.0.dist-info/WHEEL
simd_sassy-0.1.0.dist-info/licenses/LICENSE
simd_sassy-0.1.0.dist-info/RECORD
