Metadata-Version: 2.4
Name: simd-sassy
Version: 0.1.0
Classifier: Programming Language :: Rust
Classifier: Programming Language :: Python :: Implementation :: CPython
Classifier: Programming Language :: Python :: Implementation :: PyPy
License-File: LICENSE
Summary: Fast approximate string searching using SIMD
Author-email: Rick beeloo <biobeeloo@gmail.com>, Ragnar Groot Koerkamp <ragnar.grootkoerkamp@gmail.com >
License: MIT
Requires-Python: >=3.7
Project-URL: Homepage, https://github.com/RagnarGrootKoerkamp/sassy
Project-URL: Repository, https://github.com/RagnarGrootKoerkamp/sassy
Project-URL: Documentation, https://github.com/RagnarGrootKoerkamp/python/README
